tdapiclient/LICENSE-3RD-PARTY.pdf
tdapiclient/LICENSE.pdf
tdapiclient/README.md
tdapiclient/__init__.py
tdapiclient/_version.py
tdapiclient/common/__init__.py
tdapiclient/common/constants.py
tdapiclient/common/exceptions.py
tdapiclient/common/logger.py
tdapiclient/common/messagecodes.py
tdapiclient/common/messages.py
tdapiclient/common/tdsg_logger.py
tdapiclient/core/__init__.py
tdapiclient/core/tdapiclient.py
tdapiclient/utils/__init__.py
tdapiclient/utils/validators.py
tdapiclient-1.4.0.1.dist-info/METADATA
tdapiclient-1.4.0.1.dist-info/WHEEL
tdapiclient-1.4.0.1.dist-info/top_level.txt
tdapiclient-1.4.0.1.dist-info/zip-safe
tdapiclient-1.4.0.1.dist-info/RECORD
