Metadata-Version: 2.1
Name: tdapiclient
Version: 1.4.0.1
Summary: Teradata API Client Python package
Home-page: http://www.teradata.com/
Author: Teradata Corporation
License: Teradata License Agreement
Keywords: Teradata
Platform: MacOS X, Windows, Linux
Classifier: Programming Language :: Python :: 3 :: Only
Classifier: Programming Language :: Python :: 3.5
Classifier: Programming Language :: Python :: 3.6
Classifier: Programming Language :: Python :: 3.7
Classifier: Operating System :: Microsoft :: Windows
Classifier: Operating System :: MacOS :: MacOS X
Classifier: Operating System :: POSIX :: Linux
Classifier: Topic :: Database :: Front-Ends
Classifier: License :: Other/Proprietary License
Requires-Python: >=3.0
Requires-Dist: azure-mgmt-storage (>=19.0.0)
Requires-Dist: azure-storage-blob (>=12.14.0)
Requires-Dist: azureml-core (>=1.42.0)
Requires-Dist: sagemaker (>=2.75.00)
Requires-Dist: teradataml (>=17.20.00.03)
